api.py
client.py
migrate.py
server.py
utils.py
iflow_mcp_jikime_py_mcp_ko_weather-0.1.0.dist-info/METADATA
iflow_mcp_jikime_py_mcp_ko_weather-0.1.0.dist-info/WHEEL
iflow_mcp_jikime_py_mcp_ko_weather-0.1.0.dist-info/entry_points.txt
iflow_mcp_jikime_py_mcp_ko_weather-0.1.0.dist-info/top_level.txt
iflow_mcp_jikime_py_mcp_ko_weather-0.1.0.dist-info/RECORD
