Metadata-Version: 2.4
Name: iflow-mcp_jikime_py-mcp-ko-weather
Version: 0.1.0
Summary: Korea Weather
Author-email: Anthony Kim <jikime@gmail.com>
License: Apache-2.0
Requires-Python: >=3.11
Requires-Dist: pandas>=2.2.3
Requires-Dist: python-dotenv>=1.1.0
Requires-Dist: httpx>=0.28.1
Requires-Dist: mcp[cli]>=1.6.0
